video_background_extractor/Types.py
video_background_extractor/VideoBackgroundExtractor.py
video_background_extractor/__init__.py
video_background_extractor-1.3.0.dist-info/licenses/LICENSE
video_background_extractor-1.3.0.dist-info/METADATA
video_background_extractor-1.3.0.dist-info/WHEEL
video_background_extractor-1.3.0.dist-info/top_level.txt
video_background_extractor-1.3.0.dist-info/RECORD
