Metadata-Version: 2.4
Name: video-background-extractor
Version: 1.3.0
Summary: Library to extract background from static video. 
Author-email: Henrique Schmitz <sch.henrique@gmail.com>
License: MIT License
Project-URL: github, https://github.com/HenriqueSchmitz/VideoBackgroundExtractor
Classifier: Programming Language :: Python :: 3
Classifier: Operating System :: OS Independent
Requires-Python: >=3.8
License-File: LICENSE
Requires-Dist: torch>=2.3.0
Requires-Dist: numpy
Requires-Dist: opencv-python
Dynamic: license-file
